README.rst
setup.py
tracext/__init__.py
tracext/redispub/__init__.py
tracext/redispub/redis.py
tracext/redispub/ticket.py
tracext/redispub/util.py
tracext/redispub/wiki.py
tracext_redispub.egg-info/PKG-INFO
tracext_redispub.egg-info/SOURCES.txt
tracext_redispub.egg-info/dependency_links.txt
tracext_redispub.egg-info/entry_points.txt
tracext_redispub.egg-info/requires.txt
tracext_redispub.egg-info/top_level.txt