Metadata-Version: 1.1
Name: tracext-redispub
Version: 0.1
Summary: Redis pub/sub channels for Trac events
Home-page: https://github.com/embray/tracext-redispub
Author: Erik M. Bray
Author-email: erik.m.bray@gmail.com
License: BSD
Download-URL: https://pypi.python.org/pypi/tracext-redispub
Platform: all
